{
  "version": "7",
  "dialect": "sqlite",
  "entries": [
    {
      "idx": 0,
      "version": "6",
      "when": 1743219426792,
      "tag": "0000_perpetual_harrier",
      "breakpoints": true
    },
    {
      "idx": 1,
      "version": "6",
      "when": 1743740231310,
      "tag": "0001_premium_scarecrow",
      "breakpoints": true
    },
    {
      "idx": 2,
      "version": "6",
      "when": 1743797908583,
      "tag": "0002_lucky_microchip",
      "breakpoints": true
    },
    {
      "idx": 3,
      "version": "6",
      "when": 1744000976160,
      "tag": "0003_outstanding_professor_monster",
      "breakpoints": true
    },
    {
      "idx": 4,
      "version": "6",
      "when": 1744220709951,
      "tag": "0004_optimal_catseye",
      "breakpoints": true
    },
    {
      "idx": 5,
      "version": "6",
      "when": 1744224808160,
      "tag": "0005_lame_sally_floyd",
      "breakpoints": true
    },
    {
      "idx": 6,
      "version": "6",
      "when": 1744241962837,
      "tag": "0006_nappy_tiger_shark",
      "breakpoints": true
    }
  ]
}